hat/__init__.py
hat/_base.py
hat/constants.py
hat/exceptions.py
hat/modules/__init__.py
hat/modules/_base.py
hat/modules/batchnorm.py
hat/modules/conv.py
hat/modules/linear.py
hat/modules/maskers/__init__.py
hat/modules/maskers/_base.py
hat/modules/maskers/attention_masker.py
hat/modules/maskers/constant_masker.py
hat/modules/maskers/hat_masker.py
hat/modules/normalization.py
hat/modules/utils.py
hat/parameter.py
hat/payload.py
hat/timm_models/__init__.py
hat/timm_models/layers/__init__.py
hat/timm_models/layers/mlp.py
hat/timm_models/layers/patch_embed.py
hat/timm_models/resnet.py
hat/timm_models/utils/__init__.py
hat/timm_models/utils/conversion.py
hat/timm_models/vision_transformer.py
hat/types_.py
hat/utils/__init__.py
hat/utils/conversion.py
hat/utils/forgetting.py
hat/utils/forward.py
hat/utils/inspection.py
hat/utils/loading.py
hat/utils/pruning.py
hat/utils/regularization.py
hat/utils/scaling.py
hat_cl-0.1.1.dist-info/METADATA
hat_cl-0.1.1.dist-info/WHEEL
hat_cl-0.1.1.dist-info/RECORD
