Metadata-Version: 2.1
Name: hat-cl
Version: 0.1.1
Summary: HAT (Hard Attention to the Task) Modules for Continual Learning
License: MIT
Author: Xiaotian Duan
Author-email: xduan7@gmail.com
Requires-Python: >=3.9,<3.11
Classifier: License :: OSI Approved :: MIT License
Classifier: Programming Language :: Python :: 3
Classifier: Programming Language :: Python :: 3.9
Classifier: Programming Language :: Python :: 3.10
Requires-Dist: numpy (>=1.23,<2.0)
Requires-Dist: timm (>=0.6.12,<0.7.0)
Requires-Dist: torch (>=1.9.0,<2.0.0)
